pc_mouseparty/__init__.py
pc_mouseparty/cli.py
pc_mouseparty/common.py
pc_mouseparty/pc_mouseparty.py
pc_mouseparty-0.1.1.dist-info/AUTHORS.rst
pc_mouseparty-0.1.1.dist-info/LICENSE
pc_mouseparty-0.1.1.dist-info/METADATA
pc_mouseparty-0.1.1.dist-info/WHEEL
pc_mouseparty-0.1.1.dist-info/entry_points.txt
pc_mouseparty-0.1.1.dist-info/top_level.txt
pc_mouseparty-0.1.1.dist-info/RECORD
