Metadata-Version: 2.1
Name: pc-mouseparty
Version: 0.1.1
Summary: A package for all the base functions used in the Padilla-Coreano lab.
Home-page: https://github.com/padillacoreanolab/pc_mouseparty
Author: Christopher Marais
Author-email: padillacoreanolab@gmail.com
License: MIT license
Keywords: pc_mouseparty
Classifier: Intended Audience :: Developers
Classifier: License :: OSI Approved :: MIT License
Classifier: Natural Language :: English
Classifier: Programming Language :: Python :: 3
Classifier: Programming Language :: Python :: 3.8
Classifier: Programming Language :: Python :: 3.9
Classifier: Programming Language :: Python :: 3.10
Classifier: Programming Language :: Python :: 3.11
Requires-Python: >=3.8
License-File: LICENSE
License-File: AUTHORS.rst
